setup.py
chandra_proj2/__init__.py
chandra_proj2.egg-info/PKG-INFO
chandra_proj2.egg-info/SOURCES.txt
chandra_proj2.egg-info/dependency_links.txt
chandra_proj2.egg-info/not-zip-safe
chandra_proj2.egg-info/top_level.txt