Metadata-Version: 1.0
Name: chandra-proj2
Version: 0.1
Summary: The chandra_proj2 joke in the world
Home-page: http://github.com/storborg/chandra_proj2
Author: Flying Circus
Author-email: flyingcircus@example.com
License: MIT
Platform: UNKNOWN
